{
  "ad_id": "120239720732050070",
  "ad_name": "Video 17-10-25",
  "created_time": "2026-01-13T21:39:33+0100",
  "date": "2026-01-13",
  "creative_id": "1379187250346450",
  "creative_name": "Sharp suit. Fast car. Good Bracelets. Strong mindset.\n\n#stoneybracelets #superiorenergy #alphastyle 2026-01-13-4a0f21974ff6290db766b69a9c3143de",
  "object_type": "STATUS",
  "instagram_permalink_url": "https://www.instagram.com/p/DTdvAtIjLUH/",
  "headlines": [],
  "bodies": [],
  "descriptions": [],
  "ctas": [],
  "link_urls": [],
  "images": []
}